ingredient_parser/__init__.py
ingredient_parser/en.py
ingredient_parser/sv.py
ingredient_parser/sw.py
ingredient_parser/test_ingredient_parser.py
ingredient_parser/utils.py
ingredient_parser-1.0.1.dist-info/DESCRIPTION.rst
ingredient_parser-1.0.1.dist-info/METADATA
ingredient_parser-1.0.1.dist-info/metadata.json
ingredient_parser-1.0.1.dist-info/RECORD
ingredient_parser-1.0.1.dist-info/top_level.txt
ingredient_parser-1.0.1.dist-info/WHEEL
