Metadata-Version: 2.0
Name: ingredient-parser
Version: 1.0.1
Summary: Parsing English and Swedish language ingredients into name and measure of the ingredient.
Home-page: https://bitbucket.org/phoodster/ingredient-parser
Author: Mark Anderson
Author-email: mark+pypy@m3b.net
License: MIT License
Keywords: recipes ingredient parsing food
Platform: OS Independent
Classifier: Development Status :: 4 - Beta
Classifier: Intended Audience :: Developers
Classifier: License :: OSI Approved :: MIT License
Classifier: Programming Language :: Python :: 2
Classifier: Programming Language :: Python :: 2.6
Classifier: Programming Language :: Python :: 2.7
Classifier: Programming Language :: Python :: 3
Classifier: Programming Language :: Python :: 3.2
Classifier: Programming Language :: Python :: 3.3
Classifier: Programming Language :: Python :: 3.4
